{"data":[{"id":153907,"type":"ADM2","city":"Baroueli","name":"Baroueli","latitude":13.07489,"longitude":-6.57171},{"id":153885,"wikiDataId":"Q1902391","type":"ADM2","city":"Cercle de San","name":"Cercle de San","latitude":13.17895,"longitude":-5.01617},{"id":72489,"wikiDataId":"Q27690425","type":"CITY","city":"Kinmparana","name":"Kinmparana","latitude":12.84217,"longitude":-4.9245},{"id":71908,"type":"CITY","city":"Ké-Macina","name":"Ké-Macina","latitude":13.9641,"longitude":-5.35791},{"id":72506,"wikiDataId":"Q976115","type":"CITY","city":"Markala","name":"Markala","latitude":13.7021,"longitude":-6.0659},{"id":72679,"wikiDataId":"Q950460","type":"CITY","city":"San","name":"San","latitude":13.30335,"longitude":-4.89562},{"id":72641,"wikiDataId":"Q2257485","type":"CITY","city":"Sokolo","name":"Sokolo","latitude":14.7328,"longitude":-6.1219},{"id":72382,"type":"CITY","city":"Ségou","name":"Ségou","latitude":13.4317,"longitude":-6.2157}],"metadata":{"currentOffset":0,"totalCount":8}}
